striatum/__init__.py
striatum/rewardplot.py
striatum/simulation.py
striatum/bandit/__init__.py
striatum/bandit/bandit.py
striatum/bandit/exp3.py
striatum/bandit/exp4p.py
striatum/bandit/linthompsamp.py
striatum/bandit/linucb.py
striatum/bandit/ucb1.py
striatum/storage/__init__.py
striatum/storage/action.py
striatum/storage/history.py
striatum/storage/model.py
striatum/storage/recommendation.py
striatum/utils/__init__.py
striatum/utils/misc.py
striatum-0.2.5.dist-info/DESCRIPTION.rst
striatum-0.2.5.dist-info/METADATA
striatum-0.2.5.dist-info/RECORD
striatum-0.2.5.dist-info/WHEEL
striatum-0.2.5.dist-info/metadata.json
striatum-0.2.5.dist-info/top_level.txt
