Metadata-Version: 2.0
Name: striatum
Version: 0.2.5
Summary: Contextual bandit in python
Home-page: https://github.com/ntucllab/striatum
Author: Y.-A. Lin, Y.-Y. Yang
Author-email: r02922163@csie.ntu.edu.tw, b01902066@csie.ntu.edu.tw
License: UNKNOWN
Platform: UNKNOWN
Classifier: Topic :: Scientific/Engineering
Classifier: Programming Language :: Python :: 2.7
Classifier: Programming Language :: Python :: 3
Requires-Dist: matplotlib
Requires-Dist: numpy
Requires-Dist: scipy
Requires-Dist: six
